resau_routier_intelligent/__init__.py
resau_routier_intelligent/core/__init__.py
resau_routier_intelligent/core/analyseur.py
resau_routier_intelligent/core/simulateur.py
resau_routier_intelligent/data/config_reseau.json
resau_routier_intelligent/docs/make.bat
resau_routier_intelligent/docs/Makefile
resau_routier_intelligent/docs/source/conf.py
resau_routier_intelligent/docs/source/index.rst
resau_routier_intelligent/exceptions/__init__.py
resau_routier_intelligent/exceptions/ConfigFileException.py
resau_routier_intelligent/exceptions/NegativeDeltaTException.py
resau_routier_intelligent/exceptions/StatisticsCalculationException.py
resau_routier_intelligent/ios/__init__.py
resau_routier_intelligent/ios/affichage.py
resau_routier_intelligent/ios/export.py
resau_routier_intelligent/models/__init__.py
resau_routier_intelligent/models/feu_rouge.py
resau_routier_intelligent/models/reseau.py
resau_routier_intelligent/models/route.py
resau_routier_intelligent/models/vehicule.py
resau_routier_intelligent-0.2.0.dist-info/licenses/LICENSE
resau_routier_intelligent-0.2.0.dist-info/METADATA
resau_routier_intelligent-0.2.0.dist-info/WHEEL
resau_routier_intelligent-0.2.0.dist-info/RECORD
