Metadata-Version: 2.4
Name: resau_routier_intelligent
Version: 0.2.0
Summary: Un package Python pour la modélisation et la gestion d'un réseau routier intelligent.
License: MIT
License-File: LICENSE
Keywords: resau,routier,intelligent,transport,simulation
Author: Ahmed BenLazreg
Author-email: benlazregahmed328@gmail.com
Requires-Python: >=3.10,<4.0
Classifier: License :: OSI Approved :: MIT License
Classifier: Operating System :: OS Independent
Classifier: Programming Language :: Python :: 3
Classifier: Programming Language :: Python :: 3.10
Classifier: Programming Language :: Python :: 3.11
Classifier: Programming Language :: Python :: 3.12
Classifier: Programming Language :: Python :: 3.13
Classifier: Programming Language :: Python :: 3.14
Classifier: Topic :: Scientific/Engineering :: Artificial Intelligence
Classifier: Topic :: Software Development :: Libraries :: Python Modules
Project-URL: Homepage, https://github.com/BenLazregAhmed/resau_routier_intelligent
Project-URL: Repository, https://github.com/BenLazregAhmed/resau_routier_intelligent
